weather/__init__.py
weather/cli.py
weather/weather.py
sam_cli1.0-0.1.0.dist-info/LICENSE
sam_cli1.0-0.1.0.dist-info/METADATA
sam_cli1.0-0.1.0.dist-info/WHEEL
sam_cli1.0-0.1.0.dist-info/entry_points.txt
sam_cli1.0-0.1.0.dist-info/top_level.txt
sam_cli1.0-0.1.0.dist-info/RECORD
